warren/__init__.py
warren/__main__.py
warren/alembic.ini
warren/backends.py
warren/cli.py
warren/conf.py
warren/db.py
warren/exceptions.py
warren/fields.py
warren/filters.py
warren/models.py
warren/utils.py
warren/xapi.py
warren/api/__init__.py
warren/api/health.py
warren/api/v1/__init__.py
warren/factories/__init__.py
warren/factories/base.py
warren/indicators/__init__.py
warren/indicators/base.py
warren/indicators/mixins.py
warren/indicators/models.py
warren/migrations/__init__.py
warren/migrations/env.py
warren/migrations/versions/05e3da68582b_update_cache_index.py
warren/migrations/versions/2aaa9e8fc591_update_cache_schema.py
warren/migrations/versions/58a5b4238bbc_rename_cache_table.py
warren/migrations/versions/77a0f0fbb8ab_fix_duration_constraint.py
warren/migrations/versions/86ec32885672_rename_format_experience.py
warren/migrations/versions/94d0308156c1_fix_xi_time_constraint.py
warren/migrations/versions/a113f2ab4dc9_introduce_experience_index.py
warren/migrations/versions/ecc3caa6bbbd_init.py
warren/tests/__init__.py
warren/tests/conftest.py
warren/tests/test_cli.py
warren/tests/test_db.py
warren/tests/test_fields.py
warren/tests/test_filters.py
warren/tests/test_models.py
warren/tests/test_utils.py
warren/tests/test_xapi.py
warren/tests/api/__init__.py
warren/tests/api/test_health.py
warren/tests/fixtures/__init__.py
warren/tests/fixtures/app.py
warren/tests/fixtures/asynchronous.py
warren/tests/fixtures/auth.py
warren/tests/fixtures/db.py
warren/tests/indicators/__init__.py
warren/tests/indicators/test_base.py
warren/tests/indicators/test_mixins.py
warren/tests/indicators/test_models.py
warren/tests/xi/__init__.py
warren/tests/xi/client/__init__.py
warren/tests/xi/client/test_base_crud.py
warren/tests/xi/client/test_client.py
warren/tests/xi/client/test_crud_experience.py
warren/tests/xi/client/test_crud_relation.py
warren/tests/xi/indexers/__init__.py
warren/tests/xi/indexers/test_factories.py
warren/tests/xi/indexers/test_mixins.py
warren_api-0.5.0.dist-info/LICENSE.md
warren_api-0.5.0.dist-info/METADATA
warren_api-0.5.0.dist-info/WHEEL
warren_api-0.5.0.dist-info/entry_points.txt
warren_api-0.5.0.dist-info/top_level.txt
warren_api-0.5.0.dist-info/RECORD
